[
  {
    "NO": 1,
    "KODE_PTN": "1131",
    "NAMA_PTN": "UNIVERSITAS RIAU",
    "KODE_PRODI": "11311001",
    "NAMA_PRODI": "FISIKA",
    "JENJANG": "Sarjana",
    "DAYA_TAMPUNG_2026": "36",
    "PEMINAT_2025": "109",
    "JENIS_PORTOFOLIO": "Tidak Ada"
  },
  {
    "NO": 2,
    "KODE_PTN": "1131",
    "NAMA_PTN": "UNIVERSITAS RIAU",
    "KODE_PRODI": "11311002",
    "NAMA_PRODI": "KIMIA",
    "JENJANG": "Sarjana",
    "DAYA_TAMPUNG_2026": "36",
    "PEMINAT_2025": "265",
    "JENIS_PORTOFOLIO": "Tidak Ada"
  },
  {
    "NO": 3,
    "KODE_PTN": "1131",
    "NAMA_PTN": "UNIVERSITAS RIAU",
    "KODE_PRODI": "11311003",
    "NAMA_PRODI": "MATEMATIKA",
    "JENJANG": "Sarjana",
    "DAYA_TAMPUNG_2026": "27",
    "PEMINAT_2025": "168",
    "JENIS_PORTOFOLIO": "Tidak Ada"
  },
  {
    "NO": 4,
    "KODE_PTN": "1131",
    "NAMA_PTN": "UNIVERSITAS RIAU",
    "KODE_PRODI": "11311004",
    "NAMA_PRODI": "BIOLOGI",
    "JENJANG": "Sarjana",
    "DAYA_TAMPUNG_2026": "36",
    "PEMINAT_2025": "242",
    "JENIS_PORTOFOLIO": "Tidak Ada"
  },
  {
    "NO": 5,
    "KODE_PTN": "1131",
    "NAMA_PTN": "UNIVERSITAS RIAU",
    "KODE_PRODI": "11311005",
    "NAMA_PRODI": "MANAJEMEN SUMBERDAYA PERAIRAN",
    "JENJANG": "Sarjana",
    "DAYA_TAMPUNG_2026": "43",
    "PEMINAT_2025": "126",
    "JENIS_PORTOFOLIO": "Tidak Ada"
  },
  {
    "NO": 6,
    "KODE_PTN": "1131",
    "NAMA_PTN": "UNIVERSITAS RIAU",
    "KODE_PRODI": "11311006",
    "NAMA_PRODI": "BUDIDAYA PERAIRAN",
    "JENJANG": "Sarjana",
    "DAYA_TAMPUNG_2026": "52",
    "PEMINAT_2025": "128",
    "JENIS_PORTOFOLIO": "Tidak Ada"
  },
  {
    "NO": 7,
    "KODE_PTN": "1131",
    "NAMA_PTN": "UNIVERSITAS RIAU",
    "KODE_PRODI": "11311007",
    "NAMA_PRODI": "ILMU KELAUTAN",
    "JENJANG": "Sarjana",
    "DAYA_TAMPUNG_2026": "46",
    "PEMINAT_2025": "163",
    "JENIS_PORTOFOLIO": "Tidak Ada"
  },
  {
    "NO": 8,
    "KODE_PTN": "1131",
    "NAMA_PTN": "UNIVERSITAS RIAU",
    "KODE_PRODI": "11311008",
    "NAMA_PRODI": "TEKNOLOGI HASIL PERIKANAN",
    "JENJANG": "Sarjana",
    "DAYA_TAMPUNG_2026": "43",
    "PEMINAT_2025": "100",
    "JENIS_PORTOFOLIO": "Tidak Ada"
  },
  {
    "NO": 9,
    "KODE_PTN": "1131",
    "NAMA_PTN": "UNIVERSITAS RIAU",
    "KODE_PRODI": "11311009",
    "NAMA_PRODI": "PEMANFAATAN SUMBERDAYA PERIKANAN",
    "JENJANG": "Sarjana",
    "DAYA_TAMPUNG_2026": "37",
    "PEMINAT_2025": "90",
    "JENIS_PORTOFOLIO": "Tidak Ada"
  },
  {
    "NO": 10,
    "KODE_PTN": "1131",
    "NAMA_PTN": "UNIVERSITAS RIAU",
    "KODE_PRODI": "11311010",
    "NAMA_PRODI": "AGROBISNIS PERIKANAN",
    "JENJANG": "Sarjana",
    "DAYA_TAMPUNG_2026": "34",
    "PEMINAT_2025": "104",
    "JENIS_PORTOFOLIO": "Tidak Ada"
  },
  {
    "NO": 11,
    "KODE_PTN": "1131",
    "NAMA_PTN": "UNIVERSITAS RIAU",
    "KODE_PRODI": "11311011",
    "NAMA_PRODI": "AGROTEKNOLOGI",
    "JENJANG": "Sarjana",
    "DAYA_TAMPUNG_2026": "60",
    "PEMINAT_2025": "868",
    "JENIS_PORTOFOLIO": "Tidak Ada"
  },
  {
    "NO": 12,
    "KODE_PTN": "1131",
    "NAMA_PTN": "UNIVERSITAS RIAU",
    "KODE_PRODI": "11311012",
    "NAMA_PRODI": "AGRIBISNIS",
    "JENJANG": "Sarjana",
    "DAYA_TAMPUNG_2026": "36",
    "PEMINAT_2025": "743",
    "JENIS_PORTOFOLIO": "Tidak Ada"
  },
  {
    "NO": 13,
    "KODE_PTN": "1131",
    "NAMA_PTN": "UNIVERSITAS RIAU",
    "KODE_PRODI": "11311013",
    "NAMA_PRODI": "TEKNOLOGI HASIL PERTANIAN",
    "JENJANG": "Sarjana",
    "DAYA_TAMPUNG_2026": "24",
    "PEMINAT_2025": "322",
    "JENIS_PORTOFOLIO": "Tidak Ada"
  },
  {
    "NO": 14,
    "KODE_PTN": "1131",
    "NAMA_PTN": "UNIVERSITAS RIAU",
    "KODE_PRODI": "11311014",
    "NAMA_PRODI": "KEHUTANAN",
    "JENJANG": "Sarjana",
    "DAYA_TAMPUNG_2026": "36",
    "PEMINAT_2025": "397",
    "JENIS_PORTOFOLIO": "Tidak Ada"
  },
  {
    "NO": 15,
    "KODE_PTN": "1131",
    "NAMA_PTN": "UNIVERSITAS RIAU",
    "KODE_PRODI": "11311015",
    "NAMA_PRODI": "TEKNIK SIPIL",
    "JENJANG": "Sarjana",
    "DAYA_TAMPUNG_2026": "36",
    "PEMINAT_2025": "820",
    "JENIS_PORTOFOLIO": "Tidak Ada"
  },
  {
    "NO": 16,
    "KODE_PTN": "1131",
    "NAMA_PTN": "UNIVERSITAS RIAU",
    "KODE_PRODI": "11311016",
    "NAMA_PRODI": "TEKNIK KIMIA",
    "JENJANG": "Sarjana",
    "DAYA_TAMPUNG_2026": "31",
    "PEMINAT_2025": "592",
    "JENIS_PORTOFOLIO": "Tidak Ada"
  },
  {
    "NO": 17,
    "KODE_PTN": "1131",
    "NAMA_PTN": "UNIVERSITAS RIAU",
    "KODE_PRODI": "11311017",
    "NAMA_PRODI": "TEKNIK MESIN",
    "JENJANG": "Sarjana",
    "DAYA_TAMPUNG_2026": "34",
    "PEMINAT_2025": "694",
    "JENIS_PORTOFOLIO": "Tidak Ada"
  },
  {
    "NO": 18,
    "KODE_PTN": "1131",
    "NAMA_PTN": "UNIVERSITAS RIAU",
    "KODE_PRODI": "11311018",
    "NAMA_PRODI": "TEKNIK ELEKTRO",
    "JENJANG": "Sarjana",
    "DAYA_TAMPUNG_2026": "36",
    "PEMINAT_2025": "600",
    "JENIS_PORTOFOLIO": "Tidak Ada"
  },
  {
    "NO": 19,
    "KODE_PTN": "1131",
    "NAMA_PTN": "UNIVERSITAS RIAU",
    "KODE_PRODI": "11311019",
    "NAMA_PRODI": "KEDOKTERAN",
    "JENJANG": "Sarjana",
    "DAYA_TAMPUNG_2026": "48",
    "PEMINAT_2025": "1434",
    "JENIS_PORTOFOLIO": "Tidak Ada"
  },
  {
    "NO": 20,
    "KODE_PTN": "1131",
    "NAMA_PTN": "UNIVERSITAS RIAU",
    "KODE_PRODI": "11311020",
    "NAMA_PRODI": "ILMU KEPERAWATAN",
    "JENJANG": "Sarjana",
    "DAYA_TAMPUNG_2026": "63",
    "PEMINAT_2025": "1749",
    "JENIS_PORTOFOLIO": "Tidak Ada"
  },
  {
    "NO": 21,
    "KODE_PTN": "1131",
    "NAMA_PTN": "UNIVERSITAS RIAU",
    "KODE_PRODI": "11311021",
    "NAMA_PRODI": "PENDIDIKAN MATEMATIKA",
    "JENJANG": "Sarjana",
    "DAYA_TAMPUNG_2026": "24",
    "PEMINAT_2025": "458",
    "JENIS_PORTOFOLIO": "Tidak Ada"
  },
  {
    "NO": 22,
    "KODE_PTN": "1131",
    "NAMA_PTN": "UNIVERSITAS RIAU",
    "KODE_PRODI": "11311022",
    "NAMA_PRODI": "PENDIDIKAN BIOLOGI",
    "JENJANG": "Sarjana",
    "DAYA_TAMPUNG_2026": "24",
    "PEMINAT_2025": "478",
    "JENIS_PORTOFOLIO": "Tidak Ada"
  },
  {
    "NO": 23,
    "KODE_PTN": "1131",
    "NAMA_PTN": "UNIVERSITAS RIAU",
    "KODE_PRODI": "11311023",
    "NAMA_PRODI": "PENDIDIKAN FISIKA",
    "JENJANG": "Sarjana",
    "DAYA_TAMPUNG_2026": "24",
    "PEMINAT_2025": "166",
    "JENIS_PORTOFOLIO": "Tidak Ada"
  },
  {
    "NO": 24,
    "KODE_PTN": "1131",
    "NAMA_PTN": "UNIVERSITAS RIAU",
    "KODE_PRODI": "11311024",
    "NAMA_PRODI": "PENDIDIKAN KIMIA",
    "JENJANG": "Sarjana",
    "DAYA_TAMPUNG_2026": "24",
    "PEMINAT_2025": "222",
    "JENIS_PORTOFOLIO": "Tidak Ada"
  },
  {
    "NO": 25,
    "KODE_PTN": "1131",
    "NAMA_PTN": "UNIVERSITAS RIAU",
    "KODE_PRODI": "11311025",
    "NAMA_PRODI": "TEKNIK LINGKUNGAN",
    "JENJANG": "Sarjana",
    "DAYA_TAMPUNG_2026": "27",
    "PEMINAT_2025": "690",
    "JENIS_PORTOFOLIO": "Tidak Ada"
  },
  {
    "NO": 26,
    "KODE_PTN": "1131",
    "NAMA_PTN": "UNIVERSITAS RIAU",
    "KODE_PRODI": "11311026",
    "NAMA_PRODI": "ARSITEKTUR",
    "JENJANG": "Sarjana",
    "DAYA_TAMPUNG_2026": "28",
    "PEMINAT_2025": "331",
    "JENIS_PORTOFOLIO": "Tidak Ada"
  },
  {
    "NO": 27,
    "KODE_PTN": "1131",
    "NAMA_PTN": "UNIVERSITAS RIAU",
    "KODE_PRODI": "11311027",
    "NAMA_PRODI": "SISTEM INFORMASI",
    "JENJANG": "Sarjana",
    "DAYA_TAMPUNG_2026": "48",
    "PEMINAT_2025": "955",
    "JENIS_PORTOFOLIO": "Tidak Ada"
  },
  {
    "NO": 28,
    "KODE_PTN": "1131",
    "NAMA_PTN": "UNIVERSITAS RIAU",
    "KODE_PRODI": "11311028",
    "NAMA_PRODI": "TEKNIK INFORMATIKA",
    "JENJANG": "Sarjana",
    "DAYA_TAMPUNG_2026": "36",
    "PEMINAT_2025": "1502",
    "JENIS_PORTOFOLIO": "Tidak Ada"
  },
  {
    "NO": 29,
    "KODE_PTN": "1131",
    "NAMA_PTN": "UNIVERSITAS RIAU",
    "KODE_PRODI": "11311029",
    "NAMA_PRODI": "TEKNOLOGI INDUSTRI PERTANIAN",
    "JENJANG": "Sarjana",
    "DAYA_TAMPUNG_2026": "24",
    "PEMINAT_2025": "392",
    "JENIS_PORTOFOLIO": "Tidak Ada"
  },
  {
    "NO": 30,
    "KODE_PTN": "1131",
    "NAMA_PTN": "UNIVERSITAS RIAU",
    "KODE_PRODI": "11311030",
    "NAMA_PRODI": "STATISTIKA",
    "JENJANG": "Sarjana",
    "DAYA_TAMPUNG_2026": "27",
    "PEMINAT_2025": "253",
    "JENIS_PORTOFOLIO": "Tidak Ada"
  },
  {
    "NO": 31,
    "KODE_PTN": "1131",
    "NAMA_PTN": "UNIVERSITAS RIAU",
    "KODE_PRODI": "11311031",
    "NAMA_PRODI": "HUBUNGAN INTERNASIONAL",
    "JENJANG": "Sarjana",
    "DAYA_TAMPUNG_2026": "57",
    "PEMINAT_2025": "441",
    "JENIS_PORTOFOLIO": "Tidak Ada"
  },
  {
    "NO": 32,
    "KODE_PTN": "1131",
    "NAMA_PTN": "UNIVERSITAS RIAU",
    "KODE_PRODI": "11311032",
    "NAMA_PRODI": "ILMU PEMERINTAHAN",
    "JENJANG": "Sarjana",
    "DAYA_TAMPUNG_2026": "63",
    "PEMINAT_2025": "607",
    "JENIS_PORTOFOLIO": "Tidak Ada"
  },
  {
    "NO": 33,
    "KODE_PTN": "1131",
    "NAMA_PTN": "UNIVERSITAS RIAU",
    "KODE_PRODI": "11311033",
    "NAMA_PRODI": "ILMU ADMINISTRASI PUBLIK",
    "JENJANG": "Sarjana",
    "DAYA_TAMPUNG_2026": "49",
    "PEMINAT_2025": "789",
    "JENIS_PORTOFOLIO": "Tidak Ada"
  },
  {
    "NO": 34,
    "KODE_PTN": "1131",
    "NAMA_PTN": "UNIVERSITAS RIAU",
    "KODE_PRODI": "11311034",
    "NAMA_PRODI": "ILMU ADMINISTRASI BISNIS",
    "JENJANG": "Sarjana",
    "DAYA_TAMPUNG_2026": "52",
    "PEMINAT_2025": "1357",
    "JENIS_PORTOFOLIO": "Tidak Ada"
  },
  {
    "NO": 35,
    "KODE_PTN": "1131",
    "NAMA_PTN": "UNIVERSITAS RIAU",
    "KODE_PRODI": "11311035",
    "NAMA_PRODI": "SOSIOLOGI",
    "JENJANG": "Sarjana",
    "DAYA_TAMPUNG_2026": "57",
    "PEMINAT_2025": "448",
    "JENIS_PORTOFOLIO": "Tidak Ada"
  },
  {
    "NO": 36,
    "KODE_PTN": "1131",
    "NAMA_PTN": "UNIVERSITAS RIAU",
    "KODE_PRODI": "11311036",
    "NAMA_PRODI": "ILMU KOMUNIKASI",
    "JENJANG": "Sarjana",
    "DAYA_TAMPUNG_2026": "63",
    "PEMINAT_2025": "1181",
    "JENIS_PORTOFOLIO": "Tidak Ada"
  },
  {
    "NO": 37,
    "KODE_PTN": "1131",
    "NAMA_PTN": "UNIVERSITAS RIAU",
    "KODE_PRODI": "11311038",
    "NAMA_PRODI": "EKONOMI PEMBANGUNAN",
    "JENJANG": "Sarjana",
    "DAYA_TAMPUNG_2026": "48",
    "PEMINAT_2025": "386",
    "JENIS_PORTOFOLIO": "Tidak Ada"
  },
  {
    "NO": 38,
    "KODE_PTN": "1131",
    "NAMA_PTN": "UNIVERSITAS RIAU",
    "KODE_PRODI": "11311039",
    "NAMA_PRODI": "MANAJEMEN",
    "JENJANG": "Sarjana",
    "DAYA_TAMPUNG_2026": "108",
    "PEMINAT_2025": "1811",
    "JENIS_PORTOFOLIO": "Tidak Ada"
  },
  {
    "NO": 39,
    "KODE_PTN": "1131",
    "NAMA_PTN": "UNIVERSITAS RIAU",
    "KODE_PRODI": "11311040",
    "NAMA_PRODI": "AKUNTANSI",
    "JENJANG": "Sarjana",
    "DAYA_TAMPUNG_2026": "93",
    "PEMINAT_2025": "1463",
    "JENIS_PORTOFOLIO": "Tidak Ada"
  },
  {
    "NO": 40,
    "KODE_PTN": "1131",
    "NAMA_PTN": "UNIVERSITAS RIAU",
    "KODE_PRODI": "11311041",
    "NAMA_PRODI": "ILMU HUKUM",
    "JENJANG": "Sarjana",
    "DAYA_TAMPUNG_2026": "124",
    "PEMINAT_2025": "1156",
    "JENIS_PORTOFOLIO": "Tidak Ada"
  },
  {
    "NO": 41,
    "KODE_PTN": "1131",
    "NAMA_PTN": "UNIVERSITAS RIAU",
    "KODE_PRODI": "11311042",
    "NAMA_PRODI": "PENDIDIKAN EKONOMI",
    "JENJANG": "Sarjana",
    "DAYA_TAMPUNG_2026": "36",
    "PEMINAT_2025": "391",
    "JENIS_PORTOFOLIO": "Tidak Ada"
  },
  {
    "NO": 42,
    "KODE_PTN": "1131",
    "NAMA_PTN": "UNIVERSITAS RIAU",
    "KODE_PRODI": "11311043",
    "NAMA_PRODI": "PENDIDIKAN PANCASILA DAN KEWARGANEGARAAN",
    "JENJANG": "Sarjana",
    "DAYA_TAMPUNG_2026": "24",
    "PEMINAT_2025": "530",
    "JENIS_PORTOFOLIO": "Tidak Ada"
  },
  {
    "NO": 43,
    "KODE_PTN": "1131",
    "NAMA_PTN": "UNIVERSITAS RIAU",
    "KODE_PRODI": "11311044",
    "NAMA_PRODI": "PENDIDIKAN SEJARAH",
    "JENJANG": "Sarjana",
    "DAYA_TAMPUNG_2026": "24",
    "PEMINAT_2025": "414",
    "JENIS_PORTOFOLIO": "Tidak Ada"
  },
  {
    "NO": 44,
    "KODE_PTN": "1131",
    "NAMA_PTN": "UNIVERSITAS RIAU",
    "KODE_PRODI": "11311045",
    "NAMA_PRODI": "PENDIDIKAN BAHASA DAN SASTRA INDONESIA",
    "JENJANG": "Sarjana",
    "DAYA_TAMPUNG_2026": "36",
    "PEMINAT_2025": "844",
    "JENIS_PORTOFOLIO": "Tidak Ada"
  },
  {
    "NO": 45,
    "KODE_PTN": "1131",
    "NAMA_PTN": "UNIVERSITAS RIAU",
    "KODE_PRODI": "11311046",
    "NAMA_PRODI": "PENDIDIKAN BAHASA INGGRIS",
    "JENJANG": "Sarjana",
    "DAYA_TAMPUNG_2026": "36",
    "PEMINAT_2025": "651",
    "JENIS_PORTOFOLIO": "Tidak Ada"
  },
  {
    "NO": 46,
    "KODE_PTN": "1131",
    "NAMA_PTN": "UNIVERSITAS RIAU",
    "KODE_PRODI": "11311047",
    "NAMA_PRODI": "PENDIDIKAN BAHASA JEPANG",
    "JENJANG": "Sarjana",
    "DAYA_TAMPUNG_2026": "24",
    "PEMINAT_2025": "161",
    "JENIS_PORTOFOLIO": "Tidak Ada"
  },
  {
    "NO": 47,
    "KODE_PTN": "1131",
    "NAMA_PTN": "UNIVERSITAS RIAU",
    "KODE_PRODI": "11311048",
    "NAMA_PRODI": "PENDIDIKAN MASYARAKAT",
    "JENJANG": "Sarjana",
    "DAYA_TAMPUNG_2026": "24",
    "PEMINAT_2025": "68",
    "JENIS_PORTOFOLIO": "Tidak Ada"
  },
  {
    "NO": 48,
    "KODE_PTN": "1131",
    "NAMA_PTN": "UNIVERSITAS RIAU",
    "KODE_PRODI": "11311049",
    "NAMA_PRODI": "BIMBINGAN KONSELING",
    "JENJANG": "Sarjana",
    "DAYA_TAMPUNG_2026": "24",
    "PEMINAT_2025": "902",
    "JENIS_PORTOFOLIO": "Tidak Ada"
  },
  {
    "NO": 49,
    "KODE_PTN": "1131",
    "NAMA_PTN": "UNIVERSITAS RIAU",
    "KODE_PRODI": "11311050",
    "NAMA_PRODI": "PENDIDIKAN JASMANI KESEHATAN DAN REKREASI",
    "JENJANG": "Sarjana",
    "DAYA_TAMPUNG_2026": "24",
    "PEMINAT_2025": "322",
    "JENIS_PORTOFOLIO": "Olahraga"
  },
  {
    "NO": 50,
    "KODE_PTN": "1131",
    "NAMA_PTN": "UNIVERSITAS RIAU",
    "KODE_PRODI": "11311051",
    "NAMA_PRODI": "PENDIDIKAN KEPELATIHAN OLAHRAGA",
    "JENJANG": "Sarjana",
    "DAYA_TAMPUNG_2026": "24",
    "PEMINAT_2025": "206",
    "JENIS_PORTOFOLIO": "Olahraga"
  },
  {
    "NO": 51,
    "KODE_PTN": "1131",
    "NAMA_PTN": "UNIVERSITAS RIAU",
    "KODE_PRODI": "11311052",
    "NAMA_PRODI": "PENDIDIKAN GURU SEKOLAH DASAR",
    "JENJANG": "Sarjana",
    "DAYA_TAMPUNG_2026": "40",
    "PEMINAT_2025": "2021",
    "JENIS_PORTOFOLIO": "Tidak Ada"
  },
  {
    "NO": 52,
    "KODE_PTN": "1131",
    "NAMA_PTN": "UNIVERSITAS RIAU",
    "KODE_PRODI": "11311053",
    "NAMA_PRODI": "PENDIDIKAN ANAK USIA DINI",
    "JENJANG": "Sarjana",
    "DAYA_TAMPUNG_2026": "24",
    "PEMINAT_2025": "245",
    "JENIS_PORTOFOLIO": "Tidak Ada"
  },
  {
    "NO": 53,
    "KODE_PTN": "1131",
    "NAMA_PTN": "UNIVERSITAS RIAU",
    "KODE_PRODI": "11311062",
    "NAMA_PRODI": "KEDOKTERAN HEWAN",
    "JENJANG": "Sarjana",
    "DAYA_TAMPUNG_2026": "15",
    "PEMINAT_2025": "248",
    "JENIS_PORTOFOLIO": "Tidak Ada"
  },
  {
    "NO": 54,
    "KODE_PTN": "1131",
    "NAMA_PTN": "UNIVERSITAS RIAU",
    "KODE_PRODI": "11311063",
    "NAMA_PRODI": "ILMU TANAH",
    "JENJANG": "Sarjana",
    "DAYA_TAMPUNG_2026": "12",
    "PEMINAT_2025": "79",
    "JENIS_PORTOFOLIO": "Tidak Ada"
  },
  {
    "NO": 55,
    "KODE_PTN": "1131",
    "NAMA_PTN": "UNIVERSITAS RIAU",
    "KODE_PRODI": "11311064",
    "NAMA_PRODI": "PROTEKSI TANAMAN",
    "JENJANG": "Sarjana",
    "DAYA_TAMPUNG_2026": "12",
    "PEMINAT_2025": "52",
    "JENIS_PORTOFOLIO": "Tidak Ada"
  },
  {
    "NO": 56,
    "KODE_PTN": "1131",
    "NAMA_PTN": "UNIVERSITAS RIAU",
    "KODE_PRODI": "11311065",
    "NAMA_PRODI": "PENYULUHAN PERTANIAN",
    "JENJANG": "Sarjana",
    "DAYA_TAMPUNG_2026": "12",
    "PEMINAT_2025": "83",
    "JENIS_PORTOFOLIO": "Tidak Ada"
  },
  {
    "NO": 57,
    "KODE_PTN": "1131",
    "NAMA_PTN": "UNIVERSITAS RIAU",
    "KODE_PRODI": "11312037",
    "NAMA_PRODI": "USAHA PERJALANAN WISATA",
    "JENJANG": "Sarjana Terapan",
    "DAYA_TAMPUNG_2026": "42",
    "PEMINAT_2025": "231",
    "JENIS_PORTOFOLIO": "Tidak Ada"
  },
  {
    "NO": 58,
    "KODE_PTN": "1131",
    "NAMA_PTN": "UNIVERSITAS RIAU",
    "KODE_PRODI": "11313054",
    "NAMA_PRODI": "PERPAJAKAN",
    "JENJANG": "Diploma Tiga",
    "DAYA_TAMPUNG_2026": "36",
    "PEMINAT_2025": "160",
    "JENIS_PORTOFOLIO": "Tidak Ada"
  },
  {
    "NO": 59,
    "KODE_PTN": "1131",
    "NAMA_PTN": "UNIVERSITAS RIAU",
    "KODE_PRODI": "11313055",
    "NAMA_PRODI": "TEKNIK KIMIA",
    "JENJANG": "Diploma Tiga",
    "DAYA_TAMPUNG_2026": "27",
    "PEMINAT_2025": "48",
    "JENIS_PORTOFOLIO": "Tidak Ada"
  },
  {
    "NO": 60,
    "KODE_PTN": "1131",
    "NAMA_PTN": "UNIVERSITAS RIAU",
    "KODE_PRODI": "11313056",
    "NAMA_PRODI": "AKUNTANSI",
    "JENJANG": "Diploma Tiga",
    "DAYA_TAMPUNG_2026": "36",
    "PEMINAT_2025": "77",
    "JENIS_PORTOFOLIO": "Tidak Ada"
  },
  {
    "NO": 61,
    "KODE_PTN": "1131",
    "NAMA_PTN": "UNIVERSITAS RIAU",
    "KODE_PRODI": "11313057",
    "NAMA_PRODI": "TEKNIK ELEKTRO",
    "JENJANG": "Diploma Tiga",
    "DAYA_TAMPUNG_2026": "18",
    "PEMINAT_2025": "48",
    "JENIS_PORTOFOLIO": "Tidak Ada"
  },
  {
    "NO": 62,
    "KODE_PTN": "1131",
    "NAMA_PTN": "UNIVERSITAS RIAU",
    "KODE_PRODI": "11313058",
    "NAMA_PRODI": "TEKNIK MESIN",
    "JENJANG": "Diploma Tiga",
    "DAYA_TAMPUNG_2026": "18",
    "PEMINAT_2025": "70",
    "JENIS_PORTOFOLIO": "Tidak Ada"
  },
  {
    "NO": 63,
    "KODE_PTN": "1131",
    "NAMA_PTN": "UNIVERSITAS RIAU",
    "KODE_PRODI": "11313059",
    "NAMA_PRODI": "TEKNOLOGI PULP DAN KERTAS",
    "JENJANG": "Diploma Tiga",
    "DAYA_TAMPUNG_2026": "18",
    "PEMINAT_2025": "161",
    "JENIS_PORTOFOLIO": "Tidak Ada"
  },
  {
    "NO": 64,
    "KODE_PTN": "1131",
    "NAMA_PTN": "UNIVERSITAS RIAU",
    "KODE_PRODI": "11313060",
    "NAMA_PRODI": "TEKNIK SIPIL",
    "JENJANG": "Diploma Tiga",
    "DAYA_TAMPUNG_2026": "27",
    "PEMINAT_2025": "57",
    "JENIS_PORTOFOLIO": "Tidak Ada"
  },
  {
    "NO": 65,
    "KODE_PTN": "1131",
    "NAMA_PTN": "UNIVERSITAS RIAU",
    "KODE_PRODI": "11313061",
    "NAMA_PRODI": "MANAJEMEN INFORMATIKA",
    "JENJANG": "Diploma Tiga",
    "DAYA_TAMPUNG_2026": "24",
    "PEMINAT_2025": "79",
    "JENIS_PORTOFOLIO": "Tidak Ada"
  }
]