[
  {
    "NO": 1,
    "KODE_PTN": "1356",
    "NAMA_PTN": "UNIVERSITAS NEGERI SEMARANG",
    "KODE_PRODI": "13561001",
    "NAMA_PRODI": "PENDIDIKAN MATEMATIKA",
    "JENJANG": "Sarjana",
    "DAYA_TAMPUNG_2026": "39",
    "PEMINAT_2025": "564",
    "JENIS_PORTOFOLIO": "Tidak Ada"
  },
  {
    "NO": 2,
    "KODE_PTN": "1356",
    "NAMA_PTN": "UNIVERSITAS NEGERI SEMARANG",
    "KODE_PRODI": "13561002",
    "NAMA_PRODI": "PENDIDIKAN FISIKA",
    "JENJANG": "Sarjana",
    "DAYA_TAMPUNG_2026": "31",
    "PEMINAT_2025": "182",
    "JENIS_PORTOFOLIO": "Tidak Ada"
  },
  {
    "NO": 3,
    "KODE_PTN": "1356",
    "NAMA_PTN": "UNIVERSITAS NEGERI SEMARANG",
    "KODE_PRODI": "13561003",
    "NAMA_PRODI": "PENDIDIKAN KIMIA",
    "JENJANG": "Sarjana",
    "DAYA_TAMPUNG_2026": "31",
    "PEMINAT_2025": "270",
    "JENIS_PORTOFOLIO": "Tidak Ada"
  },
  {
    "NO": 4,
    "KODE_PTN": "1356",
    "NAMA_PTN": "UNIVERSITAS NEGERI SEMARANG",
    "KODE_PRODI": "13561004",
    "NAMA_PRODI": "PENDIDIKAN BIOLOGI",
    "JENJANG": "Sarjana",
    "DAYA_TAMPUNG_2026": "27",
    "PEMINAT_2025": "462",
    "JENIS_PORTOFOLIO": "Tidak Ada"
  },
  {
    "NO": 5,
    "KODE_PTN": "1356",
    "NAMA_PTN": "UNIVERSITAS NEGERI SEMARANG",
    "KODE_PRODI": "13561005",
    "NAMA_PRODI": "PENDIDIKAN TEKNIK BANGUNAN",
    "JENJANG": "Sarjana",
    "DAYA_TAMPUNG_2026": "27",
    "PEMINAT_2025": "130",
    "JENIS_PORTOFOLIO": "Tidak Ada"
  },
  {
    "NO": 6,
    "KODE_PTN": "1356",
    "NAMA_PTN": "UNIVERSITAS NEGERI SEMARANG",
    "KODE_PRODI": "13561006",
    "NAMA_PRODI": "PENDIDIKAN TEKNIK MESIN",
    "JENJANG": "Sarjana",
    "DAYA_TAMPUNG_2026": "27",
    "PEMINAT_2025": "152",
    "JENIS_PORTOFOLIO": "Tidak Ada"
  },
  {
    "NO": 7,
    "KODE_PTN": "1356",
    "NAMA_PTN": "UNIVERSITAS NEGERI SEMARANG",
    "KODE_PRODI": "13561007",
    "NAMA_PRODI": "PENDIDIKAN TEKNIK ELEKTRO",
    "JENJANG": "Sarjana",
    "DAYA_TAMPUNG_2026": "27",
    "PEMINAT_2025": "133",
    "JENIS_PORTOFOLIO": "Tidak Ada"
  },
  {
    "NO": 8,
    "KODE_PTN": "1356",
    "NAMA_PTN": "UNIVERSITAS NEGERI SEMARANG",
    "KODE_PRODI": "13561008",
    "NAMA_PRODI": "ILMU KEOLAHRAGAAN",
    "JENJANG": "Sarjana",
    "DAYA_TAMPUNG_2026": "25",
    "PEMINAT_2025": "210",
    "JENIS_PORTOFOLIO": "Olahraga"
  },
  {
    "NO": 9,
    "KODE_PTN": "1356",
    "NAMA_PTN": "UNIVERSITAS NEGERI SEMARANG",
    "KODE_PRODI": "13561009",
    "NAMA_PRODI": "MATEMATIKA",
    "JENJANG": "Sarjana",
    "DAYA_TAMPUNG_2026": "18",
    "PEMINAT_2025": "207",
    "JENIS_PORTOFOLIO": "Tidak Ada"
  },
  {
    "NO": 10,
    "KODE_PTN": "1356",
    "NAMA_PTN": "UNIVERSITAS NEGERI SEMARANG",
    "KODE_PRODI": "13561010",
    "NAMA_PRODI": "FISIKA",
    "JENJANG": "Sarjana",
    "DAYA_TAMPUNG_2026": "27",
    "PEMINAT_2025": "137",
    "JENIS_PORTOFOLIO": "Tidak Ada"
  },
  {
    "NO": 11,
    "KODE_PTN": "1356",
    "NAMA_PTN": "UNIVERSITAS NEGERI SEMARANG",
    "KODE_PRODI": "13561011",
    "NAMA_PRODI": "KIMIA",
    "JENJANG": "Sarjana",
    "DAYA_TAMPUNG_2026": "20",
    "PEMINAT_2025": "229",
    "JENIS_PORTOFOLIO": "Tidak Ada"
  },
  {
    "NO": 12,
    "KODE_PTN": "1356",
    "NAMA_PTN": "UNIVERSITAS NEGERI SEMARANG",
    "KODE_PRODI": "13561012",
    "NAMA_PRODI": "BIOLOGI",
    "JENJANG": "Sarjana",
    "DAYA_TAMPUNG_2026": "20",
    "PEMINAT_2025": "268",
    "JENIS_PORTOFOLIO": "Tidak Ada"
  },
  {
    "NO": 13,
    "KODE_PTN": "1356",
    "NAMA_PTN": "UNIVERSITAS NEGERI SEMARANG",
    "KODE_PRODI": "13561013",
    "NAMA_PRODI": "KESEHATAN MASYARAKAT",
    "JENJANG": "Sarjana",
    "DAYA_TAMPUNG_2026": "58",
    "PEMINAT_2025": "1890",
    "JENIS_PORTOFOLIO": "Tidak Ada"
  },
  {
    "NO": 14,
    "KODE_PTN": "1356",
    "NAMA_PTN": "UNIVERSITAS NEGERI SEMARANG",
    "KODE_PRODI": "13561014",
    "NAMA_PRODI": "PENDIDIKAN IPA",
    "JENJANG": "Sarjana",
    "DAYA_TAMPUNG_2026": "25",
    "PEMINAT_2025": "294",
    "JENIS_PORTOFOLIO": "Tidak Ada"
  },
  {
    "NO": 15,
    "KODE_PTN": "1356",
    "NAMA_PTN": "UNIVERSITAS NEGERI SEMARANG",
    "KODE_PRODI": "13561015",
    "NAMA_PRODI": "PEND. TEKNIK INFORMATIKA & KOMPUTER",
    "JENJANG": "Sarjana",
    "DAYA_TAMPUNG_2026": "24",
    "PEMINAT_2025": "357",
    "JENIS_PORTOFOLIO": "Tidak Ada"
  },
  {
    "NO": 16,
    "KODE_PTN": "1356",
    "NAMA_PTN": "UNIVERSITAS NEGERI SEMARANG",
    "KODE_PRODI": "13561016",
    "NAMA_PRODI": "TEKNIK ARSITEKTUR",
    "JENJANG": "Sarjana",
    "DAYA_TAMPUNG_2026": "33",
    "PEMINAT_2025": "404",
    "JENIS_PORTOFOLIO": "Tidak Ada"
  },
  {
    "NO": 17,
    "KODE_PTN": "1356",
    "NAMA_PTN": "UNIVERSITAS NEGERI SEMARANG",
    "KODE_PRODI": "13561017",
    "NAMA_PRODI": "PENDIDIKAN TEKNIK OTOMOTIF",
    "JENJANG": "Sarjana",
    "DAYA_TAMPUNG_2026": "27",
    "PEMINAT_2025": "277",
    "JENIS_PORTOFOLIO": "Tidak Ada"
  },
  {
    "NO": 18,
    "KODE_PTN": "1356",
    "NAMA_PTN": "UNIVERSITAS NEGERI SEMARANG",
    "KODE_PRODI": "13561018",
    "NAMA_PRODI": "TEKNIK KIMIA",
    "JENJANG": "Sarjana",
    "DAYA_TAMPUNG_2026": "33",
    "PEMINAT_2025": "375",
    "JENIS_PORTOFOLIO": "Tidak Ada"
  },
  {
    "NO": 19,
    "KODE_PTN": "1356",
    "NAMA_PTN": "UNIVERSITAS NEGERI SEMARANG",
    "KODE_PRODI": "13561019",
    "NAMA_PRODI": "TEKNIK MESIN",
    "JENJANG": "Sarjana",
    "DAYA_TAMPUNG_2026": "38",
    "PEMINAT_2025": "801",
    "JENIS_PORTOFOLIO": "Tidak Ada"
  },
  {
    "NO": 20,
    "KODE_PTN": "1356",
    "NAMA_PTN": "UNIVERSITAS NEGERI SEMARANG",
    "KODE_PRODI": "13561020",
    "NAMA_PRODI": "TEKNIK SIPIL",
    "JENJANG": "Sarjana",
    "DAYA_TAMPUNG_2026": "38",
    "PEMINAT_2025": "708",
    "JENIS_PORTOFOLIO": "Tidak Ada"
  },
  {
    "NO": 21,
    "KODE_PTN": "1356",
    "NAMA_PTN": "UNIVERSITAS NEGERI SEMARANG",
    "KODE_PRODI": "13561021",
    "NAMA_PRODI": "TEKNIK INFORMATIKA",
    "JENJANG": "Sarjana",
    "DAYA_TAMPUNG_2026": "39",
    "PEMINAT_2025": "1341",
    "JENIS_PORTOFOLIO": "Tidak Ada"
  },
  {
    "NO": 22,
    "KODE_PTN": "1356",
    "NAMA_PTN": "UNIVERSITAS NEGERI SEMARANG",
    "KODE_PRODI": "13561022",
    "NAMA_PRODI": "TEKNIK ELEKTRO",
    "JENJANG": "Sarjana",
    "DAYA_TAMPUNG_2026": "33",
    "PEMINAT_2025": "509",
    "JENIS_PORTOFOLIO": "Tidak Ada"
  },
  {
    "NO": 23,
    "KODE_PTN": "1356",
    "NAMA_PTN": "UNIVERSITAS NEGERI SEMARANG",
    "KODE_PRODI": "13561023",
    "NAMA_PRODI": "GIZI",
    "JENJANG": "Sarjana",
    "DAYA_TAMPUNG_2026": "38",
    "PEMINAT_2025": "866",
    "JENIS_PORTOFOLIO": "Tidak Ada"
  },
  {
    "NO": 24,
    "KODE_PTN": "1356",
    "NAMA_PTN": "UNIVERSITAS NEGERI SEMARANG",
    "KODE_PRODI": "13561024",
    "NAMA_PRODI": "SISTEM INFORMASI",
    "JENJANG": "Sarjana",
    "DAYA_TAMPUNG_2026": "23",
    "PEMINAT_2025": "653",
    "JENIS_PORTOFOLIO": "Tidak Ada"
  },
  {
    "NO": 25,
    "KODE_PTN": "1356",
    "NAMA_PTN": "UNIVERSITAS NEGERI SEMARANG",
    "KODE_PRODI": "13561025",
    "NAMA_PRODI": "ILMU LINGKUNGAN",
    "JENJANG": "Sarjana",
    "DAYA_TAMPUNG_2026": "21",
    "PEMINAT_2025": "325",
    "JENIS_PORTOFOLIO": "Tidak Ada"
  },
  {
    "NO": 26,
    "KODE_PTN": "1356",
    "NAMA_PTN": "UNIVERSITAS NEGERI SEMARANG",
    "KODE_PRODI": "13561026",
    "NAMA_PRODI": "FARMASI",
    "JENJANG": "Sarjana",
    "DAYA_TAMPUNG_2026": "30",
    "PEMINAT_2025": "1202",
    "JENIS_PORTOFOLIO": "Tidak Ada"
  },
  {
    "NO": 27,
    "KODE_PTN": "1356",
    "NAMA_PTN": "UNIVERSITAS NEGERI SEMARANG",
    "KODE_PRODI": "13561027",
    "NAMA_PRODI": "TEKNIK KOMPUTER",
    "JENJANG": "Sarjana",
    "DAYA_TAMPUNG_2026": "13",
    "PEMINAT_2025": "382",
    "JENIS_PORTOFOLIO": "Tidak Ada"
  },
  {
    "NO": 28,
    "KODE_PTN": "1356",
    "NAMA_PTN": "UNIVERSITAS NEGERI SEMARANG",
    "KODE_PRODI": "13561028",
    "NAMA_PRODI": "BIMBINGAN DAN KONSELING",
    "JENJANG": "Sarjana",
    "DAYA_TAMPUNG_2026": "32",
    "PEMINAT_2025": "749",
    "JENIS_PORTOFOLIO": "Tidak Ada"
  },
  {
    "NO": 29,
    "KODE_PTN": "1356",
    "NAMA_PTN": "UNIVERSITAS NEGERI SEMARANG",
    "KODE_PRODI": "13561029",
    "NAMA_PRODI": "TEKNOLOGI PENDIDIKAN",
    "JENJANG": "Sarjana",
    "DAYA_TAMPUNG_2026": "36",
    "PEMINAT_2025": "212",
    "JENIS_PORTOFOLIO": "Tidak Ada"
  },
  {
    "NO": 30,
    "KODE_PTN": "1356",
    "NAMA_PTN": "UNIVERSITAS NEGERI SEMARANG",
    "KODE_PRODI": "13561030",
    "NAMA_PRODI": "PENDIDIKAN NON FORMAL",
    "JENJANG": "Sarjana",
    "DAYA_TAMPUNG_2026": "30",
    "PEMINAT_2025": "100",
    "JENIS_PORTOFOLIO": "Tidak Ada"
  },
  {
    "NO": 31,
    "KODE_PTN": "1356",
    "NAMA_PTN": "UNIVERSITAS NEGERI SEMARANG",
    "KODE_PRODI": "13561031",
    "NAMA_PRODI": "PENDIDIKAN PANCASILA & KEWARGANEGARAAN",
    "JENJANG": "Sarjana",
    "DAYA_TAMPUNG_2026": "30",
    "PEMINAT_2025": "504",
    "JENIS_PORTOFOLIO": "Tidak Ada"
  },
  {
    "NO": 32,
    "KODE_PTN": "1356",
    "NAMA_PTN": "UNIVERSITAS NEGERI SEMARANG",
    "KODE_PRODI": "13561032",
    "NAMA_PRODI": "PENDIDIKAN GEOGRAFI",
    "JENJANG": "Sarjana",
    "DAYA_TAMPUNG_2026": "20",
    "PEMINAT_2025": "275",
    "JENIS_PORTOFOLIO": "Tidak Ada"
  },
  {
    "NO": 33,
    "KODE_PTN": "1356",
    "NAMA_PTN": "UNIVERSITAS NEGERI SEMARANG",
    "KODE_PRODI": "13561033",
    "NAMA_PRODI": "PENDIDIKAN SEJARAH",
    "JENJANG": "Sarjana",
    "DAYA_TAMPUNG_2026": "20",
    "PEMINAT_2025": "319",
    "JENIS_PORTOFOLIO": "Tidak Ada"
  },
  {
    "NO": 34,
    "KODE_PTN": "1356",
    "NAMA_PTN": "UNIVERSITAS NEGERI SEMARANG",
    "KODE_PRODI": "13561034",
    "NAMA_PRODI": "PENDIDIKAN JASMANI, KESEHATAN & REKREASI",
    "JENJANG": "Sarjana",
    "DAYA_TAMPUNG_2026": "58",
    "PEMINAT_2025": "774",
    "JENIS_PORTOFOLIO": "Olahraga"
  },
  {
    "NO": 35,
    "KODE_PTN": "1356",
    "NAMA_PTN": "UNIVERSITAS NEGERI SEMARANG",
    "KODE_PRODI": "13561035",
    "NAMA_PRODI": "PENDIDIKAN KEPELATIHAN OLAHRAGA",
    "JENJANG": "Sarjana",
    "DAYA_TAMPUNG_2026": "43",
    "PEMINAT_2025": "471",
    "JENIS_PORTOFOLIO": "Olahraga"
  },
  {
    "NO": 36,
    "KODE_PTN": "1356",
    "NAMA_PTN": "UNIVERSITAS NEGERI SEMARANG",
    "KODE_PRODI": "13561036",
    "NAMA_PRODI": "PENDIDIKAN TATA BOGA",
    "JENJANG": "Sarjana",
    "DAYA_TAMPUNG_2026": "23",
    "PEMINAT_2025": "552",
    "JENIS_PORTOFOLIO": "Tidak Ada"
  },
  {
    "NO": 37,
    "KODE_PTN": "1356",
    "NAMA_PTN": "UNIVERSITAS NEGERI SEMARANG",
    "KODE_PRODI": "13561037",
    "NAMA_PRODI": "PENDIDIKAN TATA BUSANA",
    "JENJANG": "Sarjana",
    "DAYA_TAMPUNG_2026": "20",
    "PEMINAT_2025": "494",
    "JENIS_PORTOFOLIO": "Tidak Ada"
  },
  {
    "NO": 38,
    "KODE_PTN": "1356",
    "NAMA_PTN": "UNIVERSITAS NEGERI SEMARANG",
    "KODE_PRODI": "13561038",
    "NAMA_PRODI": "PENDIDIKAN SOSIOLOGI & ANTROPOLOGI",
    "JENJANG": "Sarjana",
    "DAYA_TAMPUNG_2026": "30",
    "PEMINAT_2025": "439",
    "JENIS_PORTOFOLIO": "Tidak Ada"
  },
  {
    "NO": 39,
    "KODE_PTN": "1356",
    "NAMA_PTN": "UNIVERSITAS NEGERI SEMARANG",
    "KODE_PRODI": "13561039",
    "NAMA_PRODI": "EKONOMI PEMBANGUNAN",
    "JENJANG": "Sarjana",
    "DAYA_TAMPUNG_2026": "63",
    "PEMINAT_2025": "670",
    "JENIS_PORTOFOLIO": "Tidak Ada"
  },
  {
    "NO": 40,
    "KODE_PTN": "1356",
    "NAMA_PTN": "UNIVERSITAS NEGERI SEMARANG",
    "KODE_PRODI": "13561040",
    "NAMA_PRODI": "MANAJEMEN",
    "JENJANG": "Sarjana",
    "DAYA_TAMPUNG_2026": "99",
    "PEMINAT_2025": "2397",
    "JENIS_PORTOFOLIO": "Tidak Ada"
  },
  {
    "NO": 41,
    "KODE_PTN": "1356",
    "NAMA_PTN": "UNIVERSITAS NEGERI SEMARANG",
    "KODE_PRODI": "13561041",
    "NAMA_PRODI": "PSIKOLOGI",
    "JENJANG": "Sarjana",
    "DAYA_TAMPUNG_2026": "49",
    "PEMINAT_2025": "1031",
    "JENIS_PORTOFOLIO": "Tidak Ada"
  },
  {
    "NO": 42,
    "KODE_PTN": "1356",
    "NAMA_PTN": "UNIVERSITAS NEGERI SEMARANG",
    "KODE_PRODI": "13561042",
    "NAMA_PRODI": "GEOGRAFI",
    "JENJANG": "Sarjana",
    "DAYA_TAMPUNG_2026": "48",
    "PEMINAT_2025": "430",
    "JENIS_PORTOFOLIO": "Tidak Ada"
  },
  {
    "NO": 43,
    "KODE_PTN": "1356",
    "NAMA_PTN": "UNIVERSITAS NEGERI SEMARANG",
    "KODE_PRODI": "13561043",
    "NAMA_PRODI": "ILMU HUKUM",
    "JENJANG": "Sarjana",
    "DAYA_TAMPUNG_2026": "188",
    "PEMINAT_2025": "1434",
    "JENIS_PORTOFOLIO": "Tidak Ada"
  },
  {
    "NO": 44,
    "KODE_PTN": "1356",
    "NAMA_PTN": "UNIVERSITAS NEGERI SEMARANG",
    "KODE_PRODI": "13561044",
    "NAMA_PRODI": "AKUNTANSI",
    "JENJANG": "Sarjana",
    "DAYA_TAMPUNG_2026": "87",
    "PEMINAT_2025": "1780",
    "JENIS_PORTOFOLIO": "Tidak Ada"
  },
  {
    "NO": 45,
    "KODE_PTN": "1356",
    "NAMA_PTN": "UNIVERSITAS NEGERI SEMARANG",
    "KODE_PRODI": "13561045",
    "NAMA_PRODI": "SENI RUPA (DKV,LUKIS,PTNG,GRAFIS,GBR KRIYA)",
    "JENJANG": "Sarjana",
    "DAYA_TAMPUNG_2026": "30",
    "PEMINAT_2025": "190",
    "JENIS_PORTOFOLIO": "Seni Rupa, Desain, dan Kriya"
  },
  {
    "NO": 46,
    "KODE_PTN": "1356",
    "NAMA_PTN": "UNIVERSITAS NEGERI SEMARANG",
    "KODE_PRODI": "13561046",
    "NAMA_PRODI": "PENDIDIKAN AKUNTANSI",
    "JENJANG": "Sarjana",
    "DAYA_TAMPUNG_2026": "27",
    "PEMINAT_2025": "214",
    "JENIS_PORTOFOLIO": "Tidak Ada"
  },
  {
    "NO": 47,
    "KODE_PTN": "1356",
    "NAMA_PTN": "UNIVERSITAS NEGERI SEMARANG",
    "KODE_PRODI": "13561047",
    "NAMA_PRODI": "PENDIDIKAN EKONOMI",
    "JENJANG": "Sarjana",
    "DAYA_TAMPUNG_2026": "30",
    "PEMINAT_2025": "592",
    "JENIS_PORTOFOLIO": "Tidak Ada"
  },
  {
    "NO": 48,
    "KODE_PTN": "1356",
    "NAMA_PTN": "UNIVERSITAS NEGERI SEMARANG",
    "KODE_PRODI": "13561048",
    "NAMA_PRODI": "PENDIDIKAN ADMINISTRASI PERKANTORAN",
    "JENJANG": "Sarjana",
    "DAYA_TAMPUNG_2026": "25",
    "PEMINAT_2025": "421",
    "JENIS_PORTOFOLIO": "Tidak Ada"
  },
  {
    "NO": 49,
    "KODE_PTN": "1356",
    "NAMA_PTN": "UNIVERSITAS NEGERI SEMARANG",
    "KODE_PRODI": "13561049",
    "NAMA_PRODI": "PENDIDIKAN BAHASA DAN SASTRA INDONESIA",
    "JENJANG": "Sarjana",
    "DAYA_TAMPUNG_2026": "65",
    "PEMINAT_2025": "856",
    "JENIS_PORTOFOLIO": "Tidak Ada"
  },
  {
    "NO": 50,
    "KODE_PTN": "1356",
    "NAMA_PTN": "UNIVERSITAS NEGERI SEMARANG",
    "KODE_PRODI": "13561050",
    "NAMA_PRODI": "PENDIDIKAN BAHASA INGGRIS",
    "JENJANG": "Sarjana",
    "DAYA_TAMPUNG_2026": "43",
    "PEMINAT_2025": "714",
    "JENIS_PORTOFOLIO": "Tidak Ada"
  },
  {
    "NO": 51,
    "KODE_PTN": "1356",
    "NAMA_PTN": "UNIVERSITAS NEGERI SEMARANG",
    "KODE_PRODI": "13561051",
    "NAMA_PRODI": "PENDIDIKAN BAHASA PRANCIS",
    "JENJANG": "Sarjana",
    "DAYA_TAMPUNG_2026": "25",
    "PEMINAT_2025": "48",
    "JENIS_PORTOFOLIO": "Tidak Ada"
  },
  {
    "NO": 52,
    "KODE_PTN": "1356",
    "NAMA_PTN": "UNIVERSITAS NEGERI SEMARANG",
    "KODE_PRODI": "13561052",
    "NAMA_PRODI": "PENDIDIKAN SENI RUPA",
    "JENJANG": "Sarjana",
    "DAYA_TAMPUNG_2026": "36",
    "PEMINAT_2025": "133",
    "JENIS_PORTOFOLIO": "Seni Rupa, Desain, dan Kriya"
  },
  {
    "NO": 53,
    "KODE_PTN": "1356",
    "NAMA_PTN": "UNIVERSITAS NEGERI SEMARANG",
    "KODE_PRODI": "13561053",
    "NAMA_PRODI": "SASTRA INDONESIA",
    "JENJANG": "Sarjana",
    "DAYA_TAMPUNG_2026": "20",
    "PEMINAT_2025": "289",
    "JENIS_PORTOFOLIO": "Tidak Ada"
  },
  {
    "NO": 54,
    "KODE_PTN": "1356",
    "NAMA_PTN": "UNIVERSITAS NEGERI SEMARANG",
    "KODE_PRODI": "13561054",
    "NAMA_PRODI": "SASTRA INGGRIS",
    "JENJANG": "Sarjana",
    "DAYA_TAMPUNG_2026": "39",
    "PEMINAT_2025": "544",
    "JENIS_PORTOFOLIO": "Tidak Ada"
  },
  {
    "NO": 55,
    "KODE_PTN": "1356",
    "NAMA_PTN": "UNIVERSITAS NEGERI SEMARANG",
    "KODE_PRODI": "13561055",
    "NAMA_PRODI": "SASTRA PRANCIS",
    "JENJANG": "Sarjana",
    "DAYA_TAMPUNG_2026": "27",
    "PEMINAT_2025": "89",
    "JENIS_PORTOFOLIO": "Tidak Ada"
  },
  {
    "NO": 56,
    "KODE_PTN": "1356",
    "NAMA_PTN": "UNIVERSITAS NEGERI SEMARANG",
    "KODE_PRODI": "13561056",
    "NAMA_PRODI": "ILMU SEJARAH",
    "JENJANG": "Sarjana",
    "DAYA_TAMPUNG_2026": "20",
    "PEMINAT_2025": "215",
    "JENIS_PORTOFOLIO": "Tidak Ada"
  },
  {
    "NO": 57,
    "KODE_PTN": "1356",
    "NAMA_PTN": "UNIVERSITAS NEGERI SEMARANG",
    "KODE_PRODI": "13561057",
    "NAMA_PRODI": "SASTRA JAWA",
    "JENJANG": "Sarjana",
    "DAYA_TAMPUNG_2026": "20",
    "PEMINAT_2025": "124",
    "JENIS_PORTOFOLIO": "Tidak Ada"
  },
  {
    "NO": 58,
    "KODE_PTN": "1356",
    "NAMA_PTN": "UNIVERSITAS NEGERI SEMARANG",
    "KODE_PRODI": "13561058",
    "NAMA_PRODI": "PENDIDIKAN BAHASA DAN SASTRA JAWA",
    "JENJANG": "Sarjana",
    "DAYA_TAMPUNG_2026": "40",
    "PEMINAT_2025": "337",
    "JENIS_PORTOFOLIO": "Tidak Ada"
  },
  {
    "NO": 59,
    "KODE_PTN": "1356",
    "NAMA_PTN": "UNIVERSITAS NEGERI SEMARANG",
    "KODE_PRODI": "13561059",
    "NAMA_PRODI": "P. SENI DRAMA, TARI & MUSIK (P. SENI TARI)",
    "JENJANG": "Sarjana",
    "DAYA_TAMPUNG_2026": "36",
    "PEMINAT_2025": "147",
    "JENIS_PORTOFOLIO": "Tari"
  },
  {
    "NO": 60,
    "KODE_PTN": "1356",
    "NAMA_PTN": "UNIVERSITAS NEGERI SEMARANG",
    "KODE_PRODI": "13561060",
    "NAMA_PRODI": "P. SENI DRAMA, TARI & MUSIK (P. SENI MUSIK)",
    "JENJANG": "Sarjana",
    "DAYA_TAMPUNG_2026": "40",
    "PEMINAT_2025": "133",
    "JENIS_PORTOFOLIO": "Musik"
  },
  {
    "NO": 61,
    "KODE_PTN": "1356",
    "NAMA_PTN": "UNIVERSITAS NEGERI SEMARANG",
    "KODE_PRODI": "13561061",
    "NAMA_PRODI": "PENDIDIKAN BAHASA JEPANG",
    "JENJANG": "Sarjana",
    "DAYA_TAMPUNG_2026": "20",
    "PEMINAT_2025": "305",
    "JENIS_PORTOFOLIO": "Tidak Ada"
  },
  {
    "NO": 62,
    "KODE_PTN": "1356",
    "NAMA_PTN": "UNIVERSITAS NEGERI SEMARANG",
    "KODE_PRODI": "13561062",
    "NAMA_PRODI": "PENDIDIKAN BAHASA ARAB",
    "JENJANG": "Sarjana",
    "DAYA_TAMPUNG_2026": "36",
    "PEMINAT_2025": "256",
    "JENIS_PORTOFOLIO": "Tidak Ada"
  },
  {
    "NO": 63,
    "KODE_PTN": "1356",
    "NAMA_PTN": "UNIVERSITAS NEGERI SEMARANG",
    "KODE_PRODI": "13561063",
    "NAMA_PRODI": "PENDIDIKAN GURU SEKOLAH DASAR",
    "JENJANG": "Sarjana",
    "DAYA_TAMPUNG_2026": "120",
    "PEMINAT_2025": "2787",
    "JENIS_PORTOFOLIO": "Tidak Ada"
  },
  {
    "NO": 64,
    "KODE_PTN": "1356",
    "NAMA_PTN": "UNIVERSITAS NEGERI SEMARANG",
    "KODE_PRODI": "13561064",
    "NAMA_PRODI": "PEND.GURU PEND. ANAK USIA DINI (PGPAUD)",
    "JENJANG": "Sarjana",
    "DAYA_TAMPUNG_2026": "39",
    "PEMINAT_2025": "284",
    "JENIS_PORTOFOLIO": "Tidak Ada"
  },
  {
    "NO": 65,
    "KODE_PTN": "1356",
    "NAMA_PTN": "UNIVERSITAS NEGERI SEMARANG",
    "KODE_PRODI": "13561065",
    "NAMA_PRODI": "PENDIDIKAN TATA KECANTIKAN",
    "JENJANG": "Sarjana",
    "DAYA_TAMPUNG_2026": "23",
    "PEMINAT_2025": "443",
    "JENIS_PORTOFOLIO": "Tidak Ada"
  },
  {
    "NO": 66,
    "KODE_PTN": "1356",
    "NAMA_PTN": "UNIVERSITAS NEGERI SEMARANG",
    "KODE_PRODI": "13561066",
    "NAMA_PRODI": "PENDIDIKAN BAHASA MANDARIN",
    "JENJANG": "Sarjana",
    "DAYA_TAMPUNG_2026": "12",
    "PEMINAT_2025": "134",
    "JENIS_PORTOFOLIO": "Tidak Ada"
  },
  {
    "NO": 67,
    "KODE_PTN": "1356",
    "NAMA_PTN": "UNIVERSITAS NEGERI SEMARANG",
    "KODE_PRODI": "13561067",
    "NAMA_PRODI": "ILMU POLITIK",
    "JENJANG": "Sarjana",
    "DAYA_TAMPUNG_2026": "53",
    "PEMINAT_2025": "325",
    "JENIS_PORTOFOLIO": "Tidak Ada"
  },
  {
    "NO": 68,
    "KODE_PTN": "1356",
    "NAMA_PTN": "UNIVERSITAS NEGERI SEMARANG",
    "KODE_PRODI": "13561068",
    "NAMA_PRODI": "PENDIDIKAN JASMANI SEKOLAH DASAR",
    "JENJANG": "Sarjana",
    "DAYA_TAMPUNG_2026": "20",
    "PEMINAT_2025": "238",
    "JENIS_PORTOFOLIO": "Olahraga"
  },
  {
    "NO": 69,
    "KODE_PTN": "1356",
    "NAMA_PTN": "UNIVERSITAS NEGERI SEMARANG",
    "KODE_PRODI": "13561070",
    "NAMA_PRODI": "PENDIDIKAN ILMU PENGETAHUAN SOSIAL",
    "JENJANG": "Sarjana",
    "DAYA_TAMPUNG_2026": "30",
    "PEMINAT_2025": "297",
    "JENIS_PORTOFOLIO": "Tidak Ada"
  },
  {
    "NO": 70,
    "KODE_PTN": "1356",
    "NAMA_PTN": "UNIVERSITAS NEGERI SEMARANG",
    "KODE_PRODI": "13561071",
    "NAMA_PRODI": "PENDIDIKAN KESEJAHTERAAN KELUARGA",
    "JENJANG": "Sarjana",
    "DAYA_TAMPUNG_2026": "15",
    "PEMINAT_2025": "165",
    "JENIS_PORTOFOLIO": "Tidak Ada"
  },
  {
    "NO": 71,
    "KODE_PTN": "1356",
    "NAMA_PTN": "UNIVERSITAS NEGERI SEMARANG",
    "KODE_PRODI": "13561074",
    "NAMA_PRODI": "STATISTIKA DAN SAINS DATA",
    "JENJANG": "Sarjana",
    "DAYA_TAMPUNG_2026": "19",
    "PEMINAT_2025": "311",
    "JENIS_PORTOFOLIO": "Tidak Ada"
  },
  {
    "NO": 72,
    "KODE_PTN": "1356",
    "NAMA_PTN": "UNIVERSITAS NEGERI SEMARANG",
    "KODE_PRODI": "13561075",
    "NAMA_PRODI": "EKONOMI DAN KEUANGAN ISLAM",
    "JENJANG": "Sarjana",
    "DAYA_TAMPUNG_2026": "19",
    "PEMINAT_2025": "287",
    "JENIS_PORTOFOLIO": "Tidak Ada"
  },
  {
    "NO": 73,
    "KODE_PTN": "1356",
    "NAMA_PTN": "UNIVERSITAS NEGERI SEMARANG",
    "KODE_PRODI": "13561076",
    "NAMA_PRODI": "KEDOKTERAN",
    "JENJANG": "Sarjana",
    "DAYA_TAMPUNG_2026": "10",
    "PEMINAT_2025": "538",
    "JENIS_PORTOFOLIO": "Tidak Ada"
  },
  {
    "NO": 74,
    "KODE_PTN": "1356",
    "NAMA_PTN": "UNIVERSITAS NEGERI SEMARANG",
    "KODE_PRODI": "13561077",
    "NAMA_PRODI": "ILMU KOMUNIKASI",
    "JENJANG": "Sarjana",
    "DAYA_TAMPUNG_2026": "27",
    "PEMINAT_2025": "1101",
    "JENIS_PORTOFOLIO": "Tidak Ada"
  },
  {
    "NO": 75,
    "KODE_PTN": "1356",
    "NAMA_PTN": "UNIVERSITAS NEGERI SEMARANG",
    "KODE_PRODI": "13561078",
    "NAMA_PRODI": "KEDOKTERAN HEWAN",
    "JENJANG": "Sarjana",
    "DAYA_TAMPUNG_2026": "10",
    "PEMINAT_2025": "",
    "JENIS_PORTOFOLIO": "Tidak Ada"
  },
  {
    "NO": 76,
    "KODE_PTN": "1356",
    "NAMA_PTN": "UNIVERSITAS NEGERI SEMARANG",
    "KODE_PRODI": "13563072",
    "NAMA_PRODI": "DESAIN KOMUNIKASI VISUAL",
    "JENJANG": "Diploma Tiga",
    "DAYA_TAMPUNG_2026": "8",
    "PEMINAT_2025": "103",
    "JENIS_PORTOFOLIO": "Seni Rupa, Desain, dan Kriya"
  },
  {
    "NO": 77,
    "KODE_PTN": "1356",
    "NAMA_PTN": "UNIVERSITAS NEGERI SEMARANG",
    "KODE_PRODI": "13563073",
    "NAMA_PRODI": "STATISTIKA TERAPAN DAN KOMPUTASI",
    "JENJANG": "Diploma Tiga",
    "DAYA_TAMPUNG_2026": "8",
    "PEMINAT_2025": "72",
    "JENIS_PORTOFOLIO": "Tidak Ada"
  }
]