[
  {
    "NO": 1,
    "KODE_PTN": "1551",
    "NAMA_PTN": "UNIVERSITAS BORNEO TARAKAN",
    "KODE_PRODI": "15511001",
    "NAMA_PRODI": "TEKNIK ELEKTRO",
    "JENJANG": "Sarjana",
    "DAYA_TAMPUNG_2026": "22",
    "PEMINAT_2025": "81",
    "JENIS_PORTOFOLIO": "Tidak Ada"
  },
  {
    "NO": 2,
    "KODE_PTN": "1551",
    "NAMA_PTN": "UNIVERSITAS BORNEO TARAKAN",
    "KODE_PRODI": "15511002",
    "NAMA_PRODI": "TEKNIK SIPIL",
    "JENJANG": "Sarjana",
    "DAYA_TAMPUNG_2026": "32",
    "PEMINAT_2025": "197",
    "JENIS_PORTOFOLIO": "Tidak Ada"
  },
  {
    "NO": 3,
    "KODE_PTN": "1551",
    "NAMA_PTN": "UNIVERSITAS BORNEO TARAKAN",
    "KODE_PRODI": "15511003",
    "NAMA_PRODI": "AGRIBISNIS",
    "JENJANG": "Sarjana",
    "DAYA_TAMPUNG_2026": "36",
    "PEMINAT_2025": "92",
    "JENIS_PORTOFOLIO": "Tidak Ada"
  },
  {
    "NO": 4,
    "KODE_PTN": "1551",
    "NAMA_PTN": "UNIVERSITAS BORNEO TARAKAN",
    "KODE_PRODI": "15511004",
    "NAMA_PRODI": "AGROTEKNOLOGI",
    "JENJANG": "Sarjana",
    "DAYA_TAMPUNG_2026": "30",
    "PEMINAT_2025": "65",
    "JENIS_PORTOFOLIO": "Tidak Ada"
  },
  {
    "NO": 5,
    "KODE_PTN": "1551",
    "NAMA_PTN": "UNIVERSITAS BORNEO TARAKAN",
    "KODE_PRODI": "15511005",
    "NAMA_PRODI": "PENDIDIKAN MATEMATIKA",
    "JENJANG": "Sarjana",
    "DAYA_TAMPUNG_2026": "25",
    "PEMINAT_2025": "40",
    "JENIS_PORTOFOLIO": "Tidak Ada"
  },
  {
    "NO": 6,
    "KODE_PTN": "1551",
    "NAMA_PTN": "UNIVERSITAS BORNEO TARAKAN",
    "KODE_PRODI": "15511006",
    "NAMA_PRODI": "PENDIDIKAN BIOLOGI",
    "JENJANG": "Sarjana",
    "DAYA_TAMPUNG_2026": "25",
    "PEMINAT_2025": "38",
    "JENIS_PORTOFOLIO": "Tidak Ada"
  },
  {
    "NO": 7,
    "KODE_PTN": "1551",
    "NAMA_PTN": "UNIVERSITAS BORNEO TARAKAN",
    "KODE_PRODI": "15511007",
    "NAMA_PRODI": "MANAJEMEN SUMBER DAYA PERAIRAN",
    "JENJANG": "Sarjana",
    "DAYA_TAMPUNG_2026": "24",
    "PEMINAT_2025": "25",
    "JENIS_PORTOFOLIO": "Tidak Ada"
  },
  {
    "NO": 8,
    "KODE_PTN": "1551",
    "NAMA_PTN": "UNIVERSITAS BORNEO TARAKAN",
    "KODE_PRODI": "15511008",
    "NAMA_PRODI": "AKUAKULTUR",
    "JENJANG": "Sarjana",
    "DAYA_TAMPUNG_2026": "24",
    "PEMINAT_2025": "26",
    "JENIS_PORTOFOLIO": "Tidak Ada"
  },
  {
    "NO": 9,
    "KODE_PTN": "1551",
    "NAMA_PTN": "UNIVERSITAS BORNEO TARAKAN",
    "KODE_PRODI": "15511009",
    "NAMA_PRODI": "TEKNOLOGI HASIL PERIKANAN",
    "JENJANG": "Sarjana",
    "DAYA_TAMPUNG_2026": "24",
    "PEMINAT_2025": "35",
    "JENIS_PORTOFOLIO": "Tidak Ada"
  },
  {
    "NO": 10,
    "KODE_PTN": "1551",
    "NAMA_PTN": "UNIVERSITAS BORNEO TARAKAN",
    "KODE_PRODI": "15511010",
    "NAMA_PRODI": "TEKNIK MESIN",
    "JENJANG": "Sarjana",
    "DAYA_TAMPUNG_2026": "12",
    "PEMINAT_2025": "75",
    "JENIS_PORTOFOLIO": "Tidak Ada"
  },
  {
    "NO": 11,
    "KODE_PTN": "1551",
    "NAMA_PTN": "UNIVERSITAS BORNEO TARAKAN",
    "KODE_PRODI": "15511011",
    "NAMA_PRODI": "KEPERAWATAN",
    "JENJANG": "Sarjana",
    "DAYA_TAMPUNG_2026": "29",
    "PEMINAT_2025": "370",
    "JENIS_PORTOFOLIO": "Tidak Ada"
  },
  {
    "NO": 12,
    "KODE_PTN": "1551",
    "NAMA_PTN": "UNIVERSITAS BORNEO TARAKAN",
    "KODE_PRODI": "15511012",
    "NAMA_PRODI": "KEBIDANAN",
    "JENJANG": "Sarjana",
    "DAYA_TAMPUNG_2026": "29",
    "PEMINAT_2025": "181",
    "JENIS_PORTOFOLIO": "Tidak Ada"
  },
  {
    "NO": 13,
    "KODE_PTN": "1551",
    "NAMA_PTN": "UNIVERSITAS BORNEO TARAKAN",
    "KODE_PRODI": "15511013",
    "NAMA_PRODI": "TEKNIK KOMPUTER",
    "JENJANG": "Sarjana",
    "DAYA_TAMPUNG_2026": "12",
    "PEMINAT_2025": "198",
    "JENIS_PORTOFOLIO": "Tidak Ada"
  },
  {
    "NO": 14,
    "KODE_PTN": "1551",
    "NAMA_PTN": "UNIVERSITAS BORNEO TARAKAN",
    "KODE_PRODI": "15511014",
    "NAMA_PRODI": "BIMBINGAN DAN KONSELING",
    "JENJANG": "Sarjana",
    "DAYA_TAMPUNG_2026": "49",
    "PEMINAT_2025": "128",
    "JENIS_PORTOFOLIO": "Tidak Ada"
  },
  {
    "NO": 15,
    "KODE_PTN": "1551",
    "NAMA_PTN": "UNIVERSITAS BORNEO TARAKAN",
    "KODE_PRODI": "15511015",
    "NAMA_PRODI": "PENDIDIKAN BAHASA INDONESIA",
    "JENJANG": "Sarjana",
    "DAYA_TAMPUNG_2026": "25",
    "PEMINAT_2025": "78",
    "JENIS_PORTOFOLIO": "Tidak Ada"
  },
  {
    "NO": 16,
    "KODE_PTN": "1551",
    "NAMA_PTN": "UNIVERSITAS BORNEO TARAKAN",
    "KODE_PRODI": "15511016",
    "NAMA_PRODI": "PENDIDIKAN BAHASA INGGRIS",
    "JENJANG": "Sarjana",
    "DAYA_TAMPUNG_2026": "25",
    "PEMINAT_2025": "72",
    "JENIS_PORTOFOLIO": "Tidak Ada"
  },
  {
    "NO": 17,
    "KODE_PTN": "1551",
    "NAMA_PTN": "UNIVERSITAS BORNEO TARAKAN",
    "KODE_PRODI": "15511017",
    "NAMA_PRODI": "EKONOMI PEMBANGUNAN",
    "JENJANG": "Sarjana",
    "DAYA_TAMPUNG_2026": "36",
    "PEMINAT_2025": "134",
    "JENIS_PORTOFOLIO": "Tidak Ada"
  },
  {
    "NO": 18,
    "KODE_PTN": "1551",
    "NAMA_PTN": "UNIVERSITAS BORNEO TARAKAN",
    "KODE_PRODI": "15511018",
    "NAMA_PRODI": "MANAJEMEN",
    "JENJANG": "Sarjana",
    "DAYA_TAMPUNG_2026": "36",
    "PEMINAT_2025": "408",
    "JENIS_PORTOFOLIO": "Tidak Ada"
  },
  {
    "NO": 19,
    "KODE_PTN": "1551",
    "NAMA_PTN": "UNIVERSITAS BORNEO TARAKAN",
    "KODE_PRODI": "15511019",
    "NAMA_PRODI": "HUKUM",
    "JENJANG": "Sarjana",
    "DAYA_TAMPUNG_2026": "52",
    "PEMINAT_2025": "219",
    "JENIS_PORTOFOLIO": "Tidak Ada"
  },
  {
    "NO": 20,
    "KODE_PTN": "1551",
    "NAMA_PTN": "UNIVERSITAS BORNEO TARAKAN",
    "KODE_PRODI": "15511021",
    "NAMA_PRODI": "PENDIDIKAN GURU SEKOLAH DASAR",
    "JENJANG": "Sarjana",
    "DAYA_TAMPUNG_2026": "61",
    "PEMINAT_2025": "246",
    "JENIS_PORTOFOLIO": "Tidak Ada"
  },
  {
    "NO": 21,
    "KODE_PTN": "1551",
    "NAMA_PTN": "UNIVERSITAS BORNEO TARAKAN",
    "KODE_PRODI": "15511022",
    "NAMA_PRODI": "AKUNTANSI",
    "JENJANG": "Sarjana",
    "DAYA_TAMPUNG_2026": "33",
    "PEMINAT_2025": "241",
    "JENIS_PORTOFOLIO": "Tidak Ada"
  },
  {
    "NO": 22,
    "KODE_PTN": "1551",
    "NAMA_PTN": "UNIVERSITAS BORNEO TARAKAN",
    "KODE_PRODI": "15511025",
    "NAMA_PRODI": "KEDOKTERAN",
    "JENJANG": "Sarjana",
    "DAYA_TAMPUNG_2026": "15",
    "PEMINAT_2025": "229",
    "JENIS_PORTOFOLIO": "Tidak Ada"
  },
  {
    "NO": 23,
    "KODE_PTN": "1551",
    "NAMA_PTN": "UNIVERSITAS BORNEO TARAKAN",
    "KODE_PRODI": "15511026",
    "NAMA_PRODI": "PSIKOLOGI",
    "JENJANG": "Sarjana",
    "DAYA_TAMPUNG_2026": "14",
    "PEMINAT_2025": "107",
    "JENIS_PORTOFOLIO": "Tidak Ada"
  },
  {
    "NO": 24,
    "KODE_PTN": "1551",
    "NAMA_PTN": "UNIVERSITAS BORNEO TARAKAN",
    "KODE_PRODI": "15511027",
    "NAMA_PRODI": "HUKUM BISNIS",
    "JENJANG": "Sarjana",
    "DAYA_TAMPUNG_2026": "24",
    "PEMINAT_2025": "27",
    "JENIS_PORTOFOLIO": "Tidak Ada"
  }
]